kneeliverse/__init__.py
kneeliverse/clustering.py
kneeliverse/convex_hull.py
kneeliverse/curvature.py
kneeliverse/dfdt.py
kneeliverse/evaluation.py
kneeliverse/knee_ranking.py
kneeliverse/kneedle.py
kneeliverse/linear_fit.py
kneeliverse/lmethod.py
kneeliverse/menger.py
kneeliverse/metrics.py
kneeliverse/multi_knee.py
kneeliverse/postprocessing.py
kneeliverse/rdp.py
kneeliverse/zmethod.py
kneeliverse-1.0.dist-info/LICENSE
kneeliverse-1.0.dist-info/METADATA
kneeliverse-1.0.dist-info/WHEEL
kneeliverse-1.0.dist-info/top_level.txt
kneeliverse-1.0.dist-info/RECORD
