Metadata-Version: 2.1
Name: kneeliverse
Version: 1.0
Summary: Kneeliverse: A Universal Knee/ElbowDetection Library for Performance Curves
Home-page: https://github.com/mariolpantunes/knee
Author: Mário Antunes
Author-email: mario.antunes@ua.pt
Classifier: Programming Language :: Python :: 3
Classifier: License :: OSI Approved :: MIT License
Classifier: Operating System :: OS Independent
Requires-Python: >=3.8
License-File: LICENSE
Requires-Dist: numpy >=1.23
Requires-Dist: pyUTSAlgorithms >=0.1.2
